soundmixture/__init__.py
soundmixture/config.py
soundmixture/create_noise_files.py
soundmixture/wavegenerator.py
soundmixture/data/audio/1.wav
soundmixture/data/audio/10.wav
soundmixture/data/audio/2.wav
soundmixture/data/audio/3.wav
soundmixture/data/audio/4.wav
soundmixture/data/audio/5.wav
soundmixture/data/audio/6.wav
soundmixture/data/audio/7.wav
soundmixture/data/audio/8.wav
soundmixture/data/audio/9.wav
soundmixture/data/noise/noise1.wav
soundmixture/data/noise/noise10.wav
soundmixture/data/noise/noise2.wav
soundmixture/data/noise/noise3.wav
soundmixture/data/noise/noise4.wav
soundmixture/data/noise/noise5.wav
soundmixture/data/noise/noise6.wav
soundmixture/data/noise/noise7.wav
soundmixture/data/noise/noise8.wav
soundmixture/data/noise/noise9.wav
soundmixture/data/scaled/noise_scaled_1.wav
soundmixture/data/scaled/noise_scaled_10.wav
soundmixture/data/scaled/noise_scaled_2.wav
soundmixture/data/scaled/noise_scaled_3.wav
soundmixture/data/scaled/noise_scaled_4.wav
soundmixture/data/scaled/noise_scaled_5.wav
soundmixture/data/scaled/noise_scaled_6.wav
soundmixture/data/scaled/noise_scaled_7.wav
soundmixture/data/scaled/noise_scaled_8.wav
soundmixture/data/scaled/noise_scaled_9.wav
soundmixture-0.9.dist-info/METADATA
soundmixture-0.9.dist-info/WHEEL
soundmixture-0.9.dist-info/entry_points.txt
soundmixture-0.9.dist-info/top_level.txt
soundmixture-0.9.dist-info/RECORD
