Metadata-Version: 2.1
Name: soundmixture
Version: 0.9
Summary: generating mixture of noise and non-noise sound files
Home-page: https://github.com/aakazemaa/permutation/tree/sound
Author: Kazem Ardekanian
Author-email: kazem.ardekanian@gmail.com
License: MIT
Platform: UNKNOWN
Classifier: Programming Language :: Python :: 2
Classifier: License :: OSI Approved :: MIT License
Classifier: Operating System :: OS Independent
Requires-Dist: pydub
Requires-Dist: scipy
